CHANGES.txt
MANIFEST.in
README.rst
setup.py
js/__init__.py
js.foundation.egg-info/PKG-INFO
js.foundation.egg-info/SOURCES.txt
js.foundation.egg-info/dependency_links.txt
js.foundation.egg-info/entry_points.txt
js.foundation.egg-info/namespace_packages.txt
js.foundation.egg-info/requires.txt
js.foundation.egg-info/top_level.txt
js/foundation/__init__.py
js/foundation/resources/config.rb
js/foundation/resources/css/app.css
js/foundation/resources/css/app.min.css
js/foundation/resources/css/topbar.min.css
js/foundation/resources/img/foundation/orbit/bullets.jpg
js/foundation/resources/img/foundation/orbit/left-arrow-small.png
js/foundation/resources/img/foundation/orbit/left-arrow.png
js/foundation/resources/img/foundation/orbit/loading.gif
js/foundation/resources/img/foundation/orbit/mask-black.png
js/foundation/resources/img/foundation/orbit/pause-black.png
js/foundation/resources/img/foundation/orbit/right-arrow-small.png
js/foundation/resources/img/foundation/orbit/right-arrow.png
js/foundation/resources/img/foundation/orbit/rotator-black.png
js/foundation/resources/img/foundation/orbit/timer-black.png
js/foundation/resources/js/app.js
js/foundation/resources/js/foundation.min.js
js/foundation/resources/js/jquery.foundation.accordion.js
js/foundation/resources/js/jquery.foundation.alerts.js
js/foundation/resources/js/jquery.foundation.buttons.js
js/foundation/resources/js/jquery.foundation.clearing.js
js/foundation/resources/js/jquery.foundation.forms.js
js/foundation/resources/js/jquery.foundation.joyride.js
js/foundation/resources/js/jquery.foundation.magellan.js
js/foundation/resources/js/jquery.foundation.mediaQueryToggle.js
js/foundation/resources/js/jquery.foundation.navigation.js
js/foundation/resources/js/jquery.foundation.orbit.js
js/foundation/resources/js/jquery.foundation.reveal.js
js/foundation/resources/js/jquery.foundation.tabs.js
js/foundation/resources/js/jquery.foundation.tooltips.js
js/foundation/resources/js/jquery.foundation.topbar.js
js/foundation/resources/js/jquery.js
js/foundation/resources/js/jquery.placeholder.js
js/foundation/resources/js/modernizr.foundation.js
js/foundation/resources/sass/_settings.scss
js/foundation/resources/sass/app.scss
js/foundation/resources/sass/topbar.min.scss