Metadata-Version: 1.0
Name: js.foundation
Version: 0.1.8
Summary: Fanstatic packing of Foundation
Home-page: https://github.com/ppinette
Author: Parker Pinette
Author-email: parker@parkerpinette.com
License: UNKNOWN
Keywords: fanstatic, foundation,jquery
Platform: UNKNOWN
Classifier: Intended Audience :: Developers
Classifier: Natural Language :: English
Classifier: Operating System :: OS Independent
